microtiff/__init__.py
microtiff/ifcb.py
microtiff/lisst_holo.py
microtiff/utils.py
microtiff-0.0.4.dist-info/licenses/LICENSE
microtiff-0.0.4.dist-info/METADATA
microtiff-0.0.4.dist-info/WHEEL
microtiff-0.0.4.dist-info/top_level.txt
microtiff-0.0.4.dist-info/RECORD
