Metadata-Version: 2.4
Name: microtiff
Version: 0.0.4
Summary: A Python module and CLI tool for converting proprietary microscopy formats to TIFF with JSON metadata sidecar files.
Author-email: Alex Baldwin <contact@alexbaldwin.dev>
License: LGPL-3.0
Project-URL: Homepage, https://github.com/NOC-OI/microtiff
Project-URL: Issues, https://github.com/NOC-OI/microtiff/issues
Classifier: Programming Language :: Python :: 3
Classifier: Operating System :: OS Independent
Requires-Python: >=3.8
License-File: LICENSE
Requires-Dist: numpy>=2.0.0
Requires-Dist: pillow>=8.3.1
Dynamic: license-file
